MANIFEST.in
README.md
airflow.txt
aws.txt
azure.txt
certs.txt
checkpoint.txt
dev.txt
onelogin.txt
palo_alto.txt
requirements.txt
setup.py
sharepoint.txt
tundra.txt
./convocations/__init__.py
./convocations/version.py
./convocations/airflow/__init__.py
./convocations/aws/__init__.py
./convocations/aws/ami_helpers.py
./convocations/aws/base.py
./convocations/aws/ip_ranges.py
./convocations/aws/keypairs.py
./convocations/aws/wait_helpers.py
./convocations/aws/cfn/__init__.py
./convocations/aws/cfn/import_code_pipeline.py
./convocations/aws/cfn/import_ecs_service.py
./convocations/aws/cfn/import_instance.py
./convocations/aws/cfn/import_resource_to_cfn.py
./convocations/aws/cfn/import_route_table.py
./convocations/aws/cfn/import_security_group.py
./convocations/aws/cfn/import_subnet.py
./convocations/aws/cfn/import_vpc.py
./convocations/aws/cfn/stack_commands.py
./convocations/aws/cloudwatch/__init__.py
./convocations/aws/codeartifact/__init__.py
./convocations/aws/codebuild/__init__.py
./convocations/aws/codebuild/build.py
./convocations/aws/codebuild/detect.py
./convocations/aws/codedeploy/__init__.py
./convocations/aws/ec2/__init__.py
./convocations/aws/ec2/detect.py
./convocations/aws/ec2/networking.py
./convocations/aws/ec2/routing.py
./convocations/aws/ec2/ssh.py
./convocations/aws/ec2/volumes.py
./convocations/aws/ecs/__init__.py
./convocations/aws/ecs/service_tasks.py
./convocations/aws/ecs/task_tasks.py
./convocations/aws/efs/__init__.py
./convocations/aws/elb/__init__.py
./convocations/aws/health/__init__.py
./convocations/aws/iam/__init__.py
./convocations/aws/mgn/__init__.py
./convocations/aws/mgn/launch.py
./convocations/aws/open_id/__init__.py
./convocations/aws/organizations/__init__.py
./convocations/aws/ram/__init__.py
./convocations/aws/rds/__init__.py
./convocations/aws/redshift/__init__.py
./convocations/aws/redshift/clusters.py
./convocations/aws/reservations/__init__.py
./convocations/aws/route53/__init__.py
./convocations/aws/route53/compare.py
convocations.egg-info/PKG-INFO
convocations.egg-info/SOURCES.txt
convocations.egg-info/dependency_links.txt
convocations.egg-info/entry_points.txt
convocations.egg-info/requires.txt
convocations.egg-info/top_level.txt
